emotion_ai_api/__init__.py
emotion_ai_api/client.py
emotion_ai_api-0.1.9.dist-info/LICENSE
emotion_ai_api-0.1.9.dist-info/METADATA
emotion_ai_api-0.1.9.dist-info/WHEEL
emotion_ai_api-0.1.9.dist-info/top_level.txt
emotion_ai_api-0.1.9.dist-info/RECORD
